Python_sml_ClientInterface.py
soar_compat-1.0.dist-info/METADATA
soar_compat-1.0.dist-info/WHEEL
soar_compat-1.0.dist-info/top_level.txt
soar_compat-1.0.dist-info/RECORD
