Metadata-Version: 2.1
Name: soar-compat
Version: 1.0
Summary: Compatibility layer with soar-sml
Author-email: Jonathan de Jong <jo@jo.wtf>
License: BSD
Keywords: soar
Classifier: Programming Language :: Python :: 3
Requires-Dist: soar-sml
